{
    "name": "BlueDiamonds Repo Status",
    "identifier": "com.status.BlueDiamondsRepo",
    "subtitle": "Status of BluesRepo",
    "description": "See the status of BluesRepo from Alt/SideStore!",
    "news": [
        {
            "title": "Workflow Succeeded.",
            "identifier": "repo_status",
            "caption": "Last repo refresh: 2024-12-04 11:39:56\nLast modifed files:\n downloads/LiveContainer Unstable/com.kdt.livecontainer_3.1.0-fa54471.ipa, sidestore_repo.json",
            "date": "2024-12-04T11:39:56.220297",
            "tintColor": "#27AE60"
        }
    ]
}